pytest_axe_playwright_snapshot.py
pytest_axe_playwright_snapshot-0.0.6.dist-info/entry_points.txt
pytest_axe_playwright_snapshot-0.0.6.dist-info/LICENSE
pytest_axe_playwright_snapshot-0.0.6.dist-info/WHEEL
pytest_axe_playwright_snapshot-0.0.6.dist-info/METADATA
pytest_axe_playwright_snapshot-0.0.6.dist-info/RECORD
