Metadata-Version: 2.1
Name: pytest-axe-playwright-snapshot
Version: 0.0.6
Summary: A pytest plugin that runs Axe-core on Playwright pages and takes snapshots of the results.
Author: Pamela Fox
Requires-Python: >=3.8
Classifier: License :: OSI Approved :: MIT License
Classifier: Programming Language :: Python
Classifier: Programming Language :: Python :: 3
Classifier: Programming Language :: Python :: 3.8
Classifier: Programming Language :: Python :: 3.9
Classifier: Programming Language :: Python :: 3.10
Classifier: Programming Language :: Python :: 3.11
Classifier: Framework :: Pytest
Requires-Dist: pytest
Requires-Dist: pytest-cov
Requires-Dist: playwright
Requires-Dist: axe-playwright-python
Requires-Dist: pytest-snapshot-with-message-generator
Requires-Dist: pytest ; extra == "dev"
Requires-Dist: pytest-cov ; extra == "dev"
Requires-Dist: pytest-playwright ; extra == "dev"
Requires-Dist: pre-commit ; extra == "dev"
Requires-Dist: ruff ; extra == "dev"
Requires-Dist: black ; extra == "dev"
Requires-Dist: flit ; extra == "dev"
Project-URL: Home, https://github.com/pamelafox/pytest-axe-playwright-snapshot
Provides-Extra: dev
